creek/__init__.py
creek/automatas.py
creek/base.py
creek/infinite_sequence.py
creek/labeling.py
creek/multi_streams.py
creek/tools.py
creek/util.py
creek/scrap/__init__.py
creek/scrap/annotators.py
creek/scrap/async_utils.py
creek/scrap/creek_layers.py
creek/scrap/multi_streams.py
creek/scrap/sequences.py
creek/tests/__init__.py
creek/tests/automatas.py
creek/tests/infinite_sequence.py
creek/tests/labeling.py
creek-0.1.33.dist-info/LICENSE
creek-0.1.33.dist-info/METADATA
creek-0.1.33.dist-info/WHEEL
creek-0.1.33.dist-info/top_level.txt
creek-0.1.33.dist-info/RECORD
