Metadata-Version: 2.1
Name: creek
Version: 0.1.33
Summary: Simple streams facade
Home-page: https://github.com/i2mint/creek
Author: OtoSense
License: apache-2.0
Keywords: streams,facade
Platform: any
License-File: LICENSE
Requires-Dist: this-does-not-exist-xxxxxxxxxxxxx
